SimpleWebserviceMapper/__init__.py
SimpleWebserviceMapper/_version.py
SimpleWebserviceMapper/simplewebservice.py
interstate_love_song.SimpleWebserviceMapper-0.1.0.dist-info/LICENSE.txt
interstate_love_song.SimpleWebserviceMapper-0.1.0.dist-info/METADATA
interstate_love_song.SimpleWebserviceMapper-0.1.0.dist-info/WHEEL
interstate_love_song.SimpleWebserviceMapper-0.1.0.dist-info/entry_points.txt
interstate_love_song.SimpleWebserviceMapper-0.1.0.dist-info/top_level.txt
interstate_love_song.SimpleWebserviceMapper-0.1.0.dist-info/RECORD
